{"hive_lesson": {"title": "1463 Thailand / Laos", "description": "Abidemi talks about travels to Southeast Asia.", "audioUrl": "6c96267e-b412-4975-89c5-19f886bfa98f.mp3", "scripts": [{"hive_text_custom": {"text": "\n", "type": 0}}, {"hive_text_custom": {"text": "", "type": 0}}, {"hive_text_custom": {"text": "Todd", "type": 1}}, {"hive_text_custom": {"text": ": Abidemi, what did you do for summer break?", "type": 0}}, {"hive_text_custom": {"text": "Abidemi", "type": 1}}, {"hive_text_custom": {"text": ": For summer break, I went to visit some countries in Asia.", "type": 0}}, {"hive_text_custom": {"text": "Todd", "type": 1}}, {"hive_text_custom": {"text": ": Oh, what countries?", "type": 0}}, {"hive_text_custom": {"text": "Abidemi", "type": 1}}, {"hive_text_custom": {"text": ": I visited Thailand, Laos, Vietnam, and Myanmar.", "type": 0}}, {"hive_text_custom": {"text": "Todd", "type": 1}}, {"hive_text_custom": {"text": ": Oh, great. What did you do in each country?", "type": 0}}, {"hive_text_custom": {"text": "Abidemi", "type": 1}}, {"hive_text_custom": {"text": ": In Thailand, I was there for about a week. I ate a lot of delicious food and I met a lot of many nice people. I loved    Thailand, so I hope to return again.", "type": 0}}, {"hive_text_custom": {"text": "Todd", "type": 1}}, {"hive_text_custom": {"text": ": What foods did you eat?", "type": 0}}, {"hive_text_custom": {"text": "Abidemi", "type": 1}}, {"hive_text_custom": {"text": ": I don\u2019t remember the names but I just remembered that they were all good. (Laughter)", "type": 0}}, {"hive_text_custom": {"text": "Todd", "type": 1}}, {"hive_text_custom": {"text": ": Thai food is so good.", "type": 0}}, {"hive_text_custom": {"text": "Abidemi", "type": 1}}, {"hive_text_custom": {"text": ": Yes.", "type": 0}}, {"hive_text_custom": {"text": "Todd", "type": 1}}, {"hive_text_custom": {"text": ": Did you go anymore in Thailand like the beach or the forest?", "type": 0}}, {"hive_text_custom": {"text": "Abidemi", "type": 1}}, {"hive_text_custom": {"text": ": I was more interested in nature, so I traveled from Bangkok to Chiang Mai and Chang Rai, and I went", "type": 0}}, {"hive_text_custom": {"text": "trekking", "type": 2}}, {"hive_text_custom": {"text": "and rode elephants. So that was one of the", "type": 0}}, {"hive_text_custom": {"text": "highlights ", "type": 2}}, {"hive_text_custom": {"text": "of my trip.", "type": 0}}, {"hive_text_custom": {"text": "Todd", "type": 1}}, {"hive_text_custom": {"text": ": Oh nice. How long was the trek?", "type": 0}}, {"hive_text_custom": {"text": "Abidemi", "type": 1}}, {"hive_text_custom": {"text": ": The trek was about a day. It was a trek for 2, 3 hours but then we also stayed overnight in a community in the hills. And then the next day, we trekked for a little bit to come back to the city.", "type": 0}}, {"hive_text_custom": {"text": "Todd", "type": 1}}, {"hive_text_custom": {"text": ": Nice. So was Thailand the first stop?", "type": 0}}, {"hive_text_custom": {"text": "Abidemi", "type": 1}}, {"hive_text_custom": {"text": ": Yes. It was my first stop. It was supposed to be the shortest stop but I loved it so much that I spent more time there.", "type": 0}}, {"hive_text_custom": {"text": "Todd", "type": 1}}, {"hive_text_custom": {"text": ": After Thailand, where did you go?", "type": 0}}, {"hive_text_custom": {"text": "Abidemi", "type": 1}}, {"hive_text_custom": {"text": ": From Thailand, I", "type": 0}}, {"hive_text_custom": {"text": "moved on", "type": 2}}, {"hive_text_custom": {"text": "by land to Laos.", "type": 0}}, {"hive_text_custom": {"text": "Todd", "type": 1}}, {"hive_text_custom": {"text": ": And what did you do in Laos?", "type": 0}}, {"hive_text_custom": {"text": "Abidemi", "type": 1}}, {"hive_text_custom": {"text": ": In Laos, I mainly was in the northern part of the country, and I went", "type": 0}}, {"hive_text_custom": {"text": "zip-lining", "type": 2}}, {"hive_text_custom": {"text": ".", "type": 0}}, {"hive_text_custom": {"text": "Todd", "type": 1}}, {"hive_text_custom": {"text": ": Oh fun!", "type": 0}}, {"hive_text_custom": {"text": "Abidemi", "type": 1}}, {"hive_text_custom": {"text": ": It was fun. So\u2014", "type": 0}}, {"hive_text_custom": {"text": "Todd", "type": 1}}, {"hive_text_custom": {"text": ": So zip-lining is going flying from", "type": 0}}, {"hive_text_custom": {"text": "tree to tree", "type": 2}}, {"hive_text_custom": {"text": "?", "type": 0}}, {"hive_text_custom": {"text": "Abidemi", "type": 1}}, {"hive_text_custom": {"text": ": That\u2019s correct. So that was about two days\u2019 worth of zip-lining, and we stayed overnight in a big tree house.", "type": 0}}, {"hive_text_custom": {"text": "Todd", "type": 1}}, {"hive_text_custom": {"text": ": Oh, how fun.", "type": 0}}, {"hive_text_custom": {"text": "Abidemi", "type": 1}}, {"hive_text_custom": {"text": ": It was", "type": 0}}, {"hive_text_custom": {"text": "quite an experience", "type": 2}}, {"hive_text_custom": {"text": ".", "type": 0}}, {"hive_text_custom": {"text": "Todd", "type": 1}}, {"hive_text_custom": {"text": ": Nice.", "type": 0}}, {"hive_text_custom": {"text": "Abidemi", "type": 1}}, {"hive_text_custom": {"text": ": I really enjoyed it.", "type": 0}}], "quizs": [{"hive_lesson_quiz": {"answers": [" a) two", " b) three", " c) four"], "correct": "1", "question": "1)  She visited _____ countries. "}}, {"hive_lesson_quiz": {"answers": [" a) seven", " b) fourteen", " c) thirty"], "correct": "0", "question": "2) She was in Thailand for about _____ days. "}}, {"hive_lesson_quiz": {"answers": [" a) say", " b) remember", " c) read"], "correct": "1", "question": "3) She could not _____ the names of Thai food. "}}, {"hive_lesson_quiz": {"answers": [" a) beach", " b) forest", " c) both"], "correct": "1", "question": "4) She went to the _____ . "}}, {"hive_lesson_quiz": {"answers": [" a) a treehouse", " b) a nice resort", " c) a private villa"], "correct": "0", "question": "5) She stayed in _____ . "}}], "vocabContent": {"hive_lesson_vocab": {"vocabs": [{"hive_vocab": {"word": "trek", "audioUrl": "https://s3-us-west-1.amazonaws.com/audiovocab/1451-1500/1463-1-trek.mp3", "content": [{"hive_text_custom": {"text": "I went ", "type": 0}}, {"hive_text_custom": {"text": "trekking", "type": 2}}, {"hive_text_custom": {"text": " and rode elephants.\n\n", "type": 0}}, {"hive_text_custom": {"text": " When you go trekking that means you go hiking but for a longer stay. Notice the following:\n\n", "type": 0}}], "examples": "He went trekking in the alps.\n He carried food in his pack for his trek."}}, {"hive_vocab": {"word": "highlights", "audioUrl": "https://s3-us-west-1.amazonaws.com/audiovocab/1451-1500/1463-2-highlights.mp3", "content": [{"hive_text_custom": {"text": "That was one of the ", "type": 0}}, {"hive_text_custom": {"text": "highlights ", "type": 2}}, {"hive_text_custom": {"text": "of my trip.\n\n", "type": 0}}, {"hive_text_custom": {"text": " A highlight is one of the best parts of an event. Notice the following:\n\n", "type": 0}}], "examples": "Meeting local people was the highlight of my trip.\n For many people, having children is the highlight of their life"}}, {"hive_vocab": {"word": "move on ", "audioUrl": "https://s3-us-west-1.amazonaws.com/audiovocab/1451-1500/1463-3-move-on.mp3", "content": [{"hive_text_custom": {"text": "I ", "type": 0}}, {"hive_text_custom": {"text": "moved on", "type": 2}}, {"hive_text_custom": {"text": " by land to Laos. \n\n", "type": 0}}, {"hive_text_custom": {"text": " Here, move on means to travel or go to another place. Notice the following:\n\n", "type": 0}}], "examples": "It is late. We better move on.\n After France, we moved on to Spain."}}, {"hive_vocab": {"word": "zip-lining", "audioUrl": "https://s3-us-west-1.amazonaws.com/audiovocab/1451-1500/1463-4-zip-lining.mp3", "content": [{"hive_text_custom": {"text": "I went ", "type": 0}}, {"hive_text_custom": {"text": "zip-lining", "type": 2}}, {"hive_text_custom": {"text": ". \n\n", "type": 0}}, {"hive_text_custom": {"text": " Zip-lining is a sport that is flying in the air by a wire or cable and moving from tree-to-tree or place-to-place. Notice the following:\n\n", "type": 0}}], "examples": "He took me zip-lining for my birthday.\n He is afraid of heights, but tried zip-lining anyway."}}, {"hive_vocab": {"word": "tree to tree ", "audioUrl": "https://s3-us-west-1.amazonaws.com/audiovocab/1451-1500/1463-5-tree-to-tree.mp3", "content": [{"hive_text_custom": {"text": "Zip-lining is going  from ", "type": 0}}, {"hive_text_custom": {"text": "tree to tree", "type": 2}}, {"hive_text_custom": {"text": ".\n\n", "type": 0}}, {"hive_text_custom": {"text": " You can move tree to tree, door to door, house to house, place to pace, etc. Notice the following:\n\n", "type": 0}}], "examples": "The squirrels run tree to tree.\n He is a door-to-door salesman. "}}, {"hive_vocab": {"word": "quite an experience ", "audioUrl": "https://s3-us-west-1.amazonaws.com/audiovocab/1451-1500/1463-6-quite-an-experience.mp3", "content": [{"hive_text_custom": {"text": "It was ", "type": 0}}, {"hive_text_custom": {"text": "quite an experience", "type": 2}}, {"hive_text_custom": {"text": ".\n\n", "type": 0}}, {"hive_text_custom": {"text": " This phrase is a collocation. We often say \"quite an experience\" to mean a very memorable time. Notice the following:\n\n", "type": 0}}], "examples": "The party was quite an experience.\n My time in Europe was quite an experience."}}], "vocabQuiz": [{"hive_vocab": {"word": "", "audioUrl": "", "content": [{"hive_text_custom": {"text": "He has to", "type": 0}}, {"hive_text_custom": {"text": "move on", "type": 3}}, {"hive_text_custom": {"text": ". It is late.", "type": 0}}], "examples": ""}}, {"hive_vocab": {"word": "", "audioUrl": "", "content": [{"hive_text_custom": {"text": "Her trip was", "type": 0}}, {"hive_text_custom": {"text": "quite", "type": 3}}, {"hive_text_custom": {"text": "an experience.", "type": 0}}], "examples": ""}}, {"hive_vocab": {"word": "", "audioUrl": "", "content": [{"hive_text_custom": {"text": "I love to go", "type": 0}}, {"hive_text_custom": {"text": "zip-lining", "type": 3}}, {"hive_text_custom": {"text": "in the rain forest.", "type": 0}}], "examples": ""}}, {"hive_vocab": {"word": "", "audioUrl": "", "content": [{"hive_text_custom": {"text": "He went on a", "type": 0}}, {"hive_text_custom": {"text": "trek", "type": 3}}, {"hive_text_custom": {"text": "across the Alps.", "type": 0}}], "examples": ""}}, {"hive_vocab": {"word": "", "audioUrl": "", "content": [{"hive_text_custom": {"text": "The festival was the", "type": 0}}, {"hive_text_custom": {"text": "highlight", "type": 3}}, {"hive_text_custom": {"text": "of the trip.", "type": 0}}], "examples": ""}}, {"hive_vocab": {"word": "", "audioUrl": "", "content": [{"hive_text_custom": {"text": "The police went door", "type": 0}}, {"hive_text_custom": {"text": "to", "type": 3}}, {"hive_text_custom": {"text": "door looking for the man.", "type": 0}}], "examples": ""}}]}}}}