{"hive_lesson": {"title": "1237 Freaks and Animals", "description": "Julia and Todd discuss certain lifestyles.", "audioUrl": "1687747d-70de-4d72-af1d-b628753572ef.mp3", "scripts": [{"hive_text_custom": {"text": "Todd:", "type": 1}}, {"hive_text_custom": {"text": "So, Julia, let's talk about types of people.", "type": 0}}, {"hive_text_custom": {"text": "Julia:", "type": 1}}, {"hive_text_custom": {"text": "OK.", "type": 0}}, {"hive_text_custom": {"text": "Todd:", "type": 1}}, {"hive_text_custom": {"text": "Right, first one, are you a fitness freak?", "type": 0}}, {"hive_text_custom": {"text": "Julia:", "type": 1}}, {"hive_text_custom": {"text": "A fitness freak? I'm fairly fit but I'm not a freak. No, I'm not a fitness freak, no.", "type": 0}}, {"hive_text_custom": {"text": "Todd:", "type": 1}}, {"hive_text_custom": {"text": "So you exercise but it's not like you do it all the time?", "type": 0}}, {"hive_text_custom": {"text": "Julia: ", "type": 1}}, {"hive_text_custom": {"text": "No, and I do some unhealthy stuff as well. I like to drink and I'm a former smoker and yes, no I'm not a fitness freak.", "type": 0}}, {"hive_text_custom": {"text": "Todd:", "type": 1}}, {"hive_text_custom": {"text": "Right. I think a fitness freak is like somebody who does it, who exercises", "type": 0}}, {"hive_text_custom": {"text": "compulsively", "type": 2}}, {"hive_text_custom": {"text": ".", "type": 0}}, {"hive_text_custom": {"text": "Julia:", "type": 1}}, {"hive_text_custom": {"text": "I indulge in bad stuff too so no I'm not a fitness freak.", "type": 0}}, {"hive_text_custom": {"text": "Todd:", "type": 1}}, {"hive_text_custom": {"text": "OK, so that leads us to the next question. Are you a party animal?", "type": 0}}, {"hive_text_custom": {"text": "Julia: ", "type": 1}}, {"hive_text_custom": {"text": "Not any more. I'm too old now.", "type": 0}}, {"hive_text_custom": {"text": "Todd:", "type": 1}}, {"hive_text_custom": {"text": "When you were younger, you were a party animal?", "type": 0}}, {"hive_text_custom": {"text": "Julia:", "type": 1}}, {"hive_text_custom": {"text": "I think, yeah, that was probably the type that I most fitted into.", "type": 0}}, {"hive_text_custom": {"text": "Todd: ", "type": 1}}, {"hive_text_custom": {"text": "Nice. I was never a party animal.", "type": 0}}, {"hive_text_custom": {"text": "Julia: ", "type": 1}}, {"hive_text_custom": {"text": "No?", "type": 0}}, {"hive_text_custom": {"text": "Todd:", "type": 1}}, {"hive_text_custom": {"text": "No, I've always been pretty", "type": 0}}, {"hive_text_custom": {"text": "tame", "type": 2}}, {"hive_text_custom": {"text": ". I've always been pretty tame.", "type": 0}}, {"hive_text_custom": {"text": "Julia:", "type": 1}}, {"hive_text_custom": {"text": "Yes, I was pretty wild when I was younger.", "type": 0}}, {"hive_text_custom": {"text": "Todd:", "type": 1}}, {"hive_text_custom": {"text": "Really?", "type": 0}}, {"hive_text_custom": {"text": "Julia:", "type": 1}}, {"hive_text_custom": {"text": "Yeah.", "type": 0}}, {"hive_text_custom": {"text": "Todd:", "type": 1}}, {"hive_text_custom": {"text": "So you used to drink, smoke, stay up late?", "type": 0}}, {"hive_text_custom": {"text": "Julia:", "type": 1}}, {"hive_text_custom": {"text": "Yeah. All that and more, yeah.", "type": 0}}, {"hive_text_custom": {"text": "Todd: ", "type": 1}}, {"hive_text_custom": {"text": "Come home in the", "type": 0}}, {"hive_text_custom": {"text": "wee hours", "type": 2}}, {"hive_text_custom": {"text": "of the morning?", "type": 0}}, {"hive_text_custom": {"text": "Julia:", "type": 1}}, {"hive_text_custom": {"text": "Oh, yeah.", "type": 0}}, {"hive_text_custom": {"text": "Todd:", "type": 1}}, {"hive_text_custom": {"text": "Oh, nice, that's cool. OK, next one would be do you know anybody in your family who's a couch potato?", "type": 0}}, {"hive_text_custom": {"text": "Julia: ", "type": 1}}, {"hive_text_custom": {"text": "Couch potato?", "type": 0}}, {"hive_text_custom": {"text": "Todd:", "type": 1}}, {"hive_text_custom": {"text": "Because I know that you're not a couch potato.", "type": 0}}, {"hive_text_custom": {"text": "Julia:", "type": 1}}, {"hive_text_custom": {"text": "I'm not a couch potato, no. My brother sometimes demonstrates couch potato traits.", "type": 0}}, {"hive_text_custom": {"text": "Todd: ", "type": 1}}, {"hive_text_custom": {"text": "Yeah.", "type": 0}}, {"hive_text_custom": {"text": "Julia:", "type": 1}}, {"hive_text_custom": {"text": "He likes to play video games and stuff like that and he'll spend a lot of time watching movies and so he does spend a lot of time", "type": 0}}, {"hive_text_custom": {"text": "sedentary", "type": 2}}, {"hive_text_custom": {"text": "compared to me. He makes me look like a fitness freak, I guess, because he doesn't do so much exercise.", "type": 0}}, {"hive_text_custom": {"text": "Todd:", "type": 1}}, {"hive_text_custom": {"text": "Right. And so for people listening a couch potato is somebody who watches a lot of TV and sits on the couch.", "type": 0}}, {"hive_text_custom": {"text": "Julia:", "type": 1}}, {"hive_text_custom": {"text": "Spends a lot of time on the couch, yeah.", "type": 0}}, {"hive_text_custom": {"text": "Todd:", "type": 1}}, {"hive_text_custom": {"text": "Well, how about the similar personality trait of the bookworm? Are you a bookworm?", "type": 0}}, {"hive_text_custom": {"text": "Julia:", "type": 1}}, {"hive_text_custom": {"text": "A bookworm? No, but I think my husband's probably a bookworm.", "type": 0}}, {"hive_text_custom": {"text": "Todd:", "type": 1}}, {"hive_text_custom": {"text": "Yeah?", "type": 0}}, {"hive_text_custom": {"text": "Julia:", "type": 1}}, {"hive_text_custom": {"text": "He spends a lot of time reading books. He reads very fast so he gets through a lot of books.", "type": 0}}, {"hive_text_custom": {"text": "Todd:", "type": 1}}, {"hive_text_custom": {"text": "He's a speed reader?", "type": 0}}, {"hive_text_custom": {"text": "Julia:", "type": 1}}, {"hive_text_custom": {"text": "Yeah, he's a very fast reader and he has to read. He has to have a book with him all the time. He cannot, a waiting room or on a train or any situation where you've just got to sit around, he cannot do it if he doesn't have a book.", "type": 0}}, {"hive_text_custom": {"text": "Todd:", "type": 1}}, {"hive_text_custom": {"text": "Yeah. You know I live alone and that's a terrible trait that I have. I cannot sit and eat and just eat without something to occupy my attention. I have to read or I have to be like watching something on the computer and if I go to a waiting room or anything like that or I'm on a plane I'm the same. I have to have something to read.", "type": 0}}, {"hive_text_custom": {"text": "It drives me nuts", "type": 2}}, {"hive_text_custom": {"text": ".", "type": 0}}, {"hive_text_custom": {"text": "Julia:", "type": 1}}, {"hive_text_custom": {"text": "You see I can't read on transport because I get sick. It makes me sick, it makes me", "type": 0}}, {"hive_text_custom": {"text": "nauseous", "type": 2}}, {"hive_text_custom": {"text": ".", "type": 0}}, {"hive_text_custom": {"text": "Todd:", "type": 1}}, {"hive_text_custom": {"text": "Like motion sickness?", "type": 0}}, {"hive_text_custom": {"text": "Julia:", "type": 1}}, {"hive_text_custom": {"text": "Yeah. So I don't have a habit of reading on a train. A bus or a car, oh my God no, I can't read. No way but my husband reads everywhere all the time.", "type": 0}}], "quizs": [{"hive_lesson_quiz": {"answers": [" a) Watching TV", " b) Drinking", " c) Smoking", " d) Overeating"], "correct": "1;2", "question": "1) What are unhealthy habits Julia has or had? "}}, {"hive_lesson_quiz": {"answers": [" a) Julia", " b) Todd", " c) Julia and Todd", " d) Neither of them"], "correct": "0", "question": "2) Who was a party animal? "}}, {"hive_lesson_quiz": {"answers": [" a) Playing video games", " b) Watching movies", " c) Sleeping all day", " d) Eating on the couch"], "correct": "0;1", "question": "3) What are couch potato traits? "}}, {"hive_lesson_quiz": {"answers": [" a) On the couch", " b) On trains", " c) Waiting rooms", " d) The library"], "correct": "1;2", "question": "4) Where does Julia's husband read? "}}, {"hive_lesson_quiz": {"answers": [" a) Computer", " b) TV", " c) Music", " d) Books"], "correct": "0;3", "question": "5) What does Todd use to occupy his attention? "}}], "vocabContent": {"hive_lesson_vocab": {"vocabs": [{"hive_vocab": {"word": "compulsively ", "audioUrl": "", "content": [{"hive_text_custom": {"text": "A fitness freak is someone who exercises compulsively.\n\n", "type": 0}}, {"hive_text_custom": {"text": " If you do something 'compulsively,' you have an            irresistible desire to do it. It's like something inside of            you tells you that you must do it. Notice the following:\n\n", "type": 0}}], "examples": "It's hard to relax around him, because he compulsively              does things with his hands.She is always compulsively touching her hair."}}, {"hive_vocab": {"word": "tame ", "audioUrl": "", "content": [{"hive_text_custom": {"text": "I've always been pretty tame.\n\n", "type": 0}}, {"hive_text_custom": {"text": " Here, 'tame' is the opposite of wild. Instead of being a            crazy party boy, Todd was calmer and more relaxed. Notice            the following:\n\n", "type": 0}}], "examples": "Her boyfriend is a little too tame for her.She's usually kind of wild at bars, but she was tame              tonight."}}, {"hive_vocab": {"word": "wee hours ", "audioUrl": "", "content": [{"hive_text_custom": {"text": "Did you come home in the wee hours of the morning?\n\n", "type": 0}}, {"hive_text_custom": {"text": " The 'wee hours' of the morning would be the time when the            sun starts coming up. Notice the following:\n\n", "type": 0}}], "examples": "I'm exhausted because I was awake until the wee hours of              the morning finishing this paper last night.He always stays out until the wee hours of the morning              when he goes out with his friends."}}, {"hive_vocab": {"word": "sedentary ", "audioUrl": "", "content": [{"hive_text_custom": {"text": "He spends a lot of time sedentary compared to me.\n\n", "type": 0}}, {"hive_text_custom": {"text": " You are 'sedentary' when you don't move around very much            or do physical activity. Watching TV is a sedentary action.            Notice the following:\n\n", "type": 0}}], "examples": "After breaking her leg, she had to be completely              sedentary for six weeks.He has gained a lot of weight since he started a more              sedentary job."}}, {"hive_vocab": {"word": "drives me nuts ", "audioUrl": "", "content": [{"hive_text_custom": {"text": "I have to have something to read. It drives me nuts.\n\n", "type": 0}}, {"hive_text_custom": {"text": " Something that 'drives you nuts' irritates you or makes            you feel crazy. Notice the following:\n\n", "type": 0}}], "examples": "It drives me nuts the way he talks with food in his              mouth.This song drives him nuts, so I always play it when he              is around."}}, {"hive_vocab": {"word": "nauseous ", "audioUrl": "", "content": [{"hive_text_custom": {"text": "I can't read on transport because I get nauseous.\n\n", "type": 0}}, {"hive_text_custom": {"text": " When are 'nauseous, ' you feel like you want to vomit.            Notice the following:\n\n", "type": 0}}], "examples": "This medicine will keep you from getting nauseous in the              car.I think I ate too many sweets, because I'm feeling very              nauseous now."}}], "vocabQuiz": [{"hive_vocab": {"word": "", "audioUrl": "", "content": [{"hive_text_custom": {"text": "Don't be such a", "type": 0}}, {"hive_text_custom": {"text": "worry", "type": 3}}, {"hive_text_custom": {"text": "wart. Everything is going to be fine.", "type": 0}}], "examples": ""}}, {"hive_vocab": {"word": "", "audioUrl": "", "content": [{"hive_text_custom": {"text": "If you stay awake until the", "type": 0}}, {"hive_text_custom": {"text": "wee", "type": 3}}, {"hive_text_custom": {"text": "hours of the morning every day, you will always be tired.", "type": 0}}], "examples": ""}}, {"hive_vocab": {"word": "", "audioUrl": "", "content": [{"hive_text_custom": {"text": "That smell is kind of making me", "type": 0}}, {"hive_text_custom": {"text": "nauseous", "type": 3}}, {"hive_text_custom": {"text": ".", "type": 0}}], "examples": ""}}, {"hive_vocab": {"word": "", "audioUrl": "", "content": [{"hive_text_custom": {"text": "", "type": 0}}, {"hive_text_custom": {"text": "insomnia", "type": 3}}, {"hive_text_custom": {"text": "is a huge problem for me when I get stressed.", "type": 0}}], "examples": ""}}, {"hive_vocab": {"word": "", "audioUrl": "", "content": [{"hive_text_custom": {"text": "I need to find a job that isn't so", "type": 0}}, {"hive_text_custom": {"text": "sedentary", "type": 3}}, {"hive_text_custom": {"text": ".", "type": 0}}], "examples": ""}}, {"hive_vocab": {"word": "", "audioUrl": "", "content": [{"hive_text_custom": {"text": "His older brothers are crazy, but he's always been very", "type": 0}}, {"hive_text_custom": {"text": "tame", "type": 3}}, {"hive_text_custom": {"text": ".", "type": 0}}], "examples": ""}}, {"hive_vocab": {"word": "", "audioUrl": "", "content": [{"hive_text_custom": {"text": "It's her", "type": 0}}, {"hive_text_custom": {"text": "tendency", "type": 3}}, {"hive_text_custom": {"text": "to apologize for things that are not her fault.", "type": 0}}], "examples": ""}}, {"hive_vocab": {"word": "", "audioUrl": "", "content": [{"hive_text_custom": {"text": "She is very", "type": 0}}, {"hive_text_custom": {"text": "compulsive", "type": 3}}, {"hive_text_custom": {"text": "about doing exercise every day.", "type": 0}}], "examples": ""}}, {"hive_vocab": {"word": "", "audioUrl": "", "content": [{"hive_text_custom": {"text": "There was a women who talked on her phone almost the whole bus ride and", "type": 0}}, {"hive_text_custom": {"text": "drove", "type": 3}}, {"hive_text_custom": {"text": "me crazy.", "type": 0}}], "examples": ""}}]}}}}